{
    "Name": "CategorySelectiveSignatures",
    "BIDSVersion": "1.9.0",
    "License": "CC0",
    "Authors": [
        "Janini, Daniel",
        "Cichy, Radoslaw"
    ],
    "Acknowledgments": "This work was supported by a Humboldt Foundation Postdoctoral Research Fellowship (D.J.), German Research Council (DFG) grants (CI 241/1-3, CI 241/1-7, INST 272/297-2) (R.M.C.), and European Research Council (ERC) Consolidator grant (ERC-CoG-2024101123101) (R.M.C.). We thank the Center for Cognitive Neuroscience Berlin for their resources in conducting our fMRI experiment.",
    "HowToAcknowledge": "",
    "Funding": [
        "Humboldt Foundation Postdoctoral Research Fellowship",
        "German Research Council (DFG) grants (CI 241/1-3, CI 241/1-7, INST 272/297-2)",
        "European Research Council (ERC) Consolidator grant (ERC-CoG-2024101123101)"
    ],
    "ReferencesAndLinks": [
        ""
    ],
    "DatasetDOI": "doi:10.18112/openneuro.ds007368.v1.0.0"
}